dekdjselfmigration-0.1.12.dist-info/METADATA
dekdjselfmigration-0.1.12.dist-info/WHEEL
dekdjselfmigration-0.1.12.dist-info/entry_points.txt
dekdjselfmigration/__init__.py
dekdjselfmigration/admin/__init__.py
dekdjselfmigration/apps.py
dekdjselfmigration/management/__init__.py
dekdjselfmigration/management/commands/__init__.py
dekdjselfmigration/management/commands/ddsmdel.py
dekdjselfmigration/management/commands/ddsmfetch.py
dekdjselfmigration/management/commands/ddsmmigration.py
dekdjselfmigration/management/commands/ddsmupload.py
dekdjselfmigration/migrations/0001_initial.py
dekdjselfmigration/migrations/0002_alter_migrationrecord_options.py
dekdjselfmigration/migrations/0003_auto_20240809_0631.py
dekdjselfmigration/migrations/__init__.py
dekdjselfmigration/models/__init__.py
dekdjselfmigration/models/migrationrecord.py
dekdjselfmigration/settings.py
dekdjselfmigration-0.1.12.dist-info/RECORD
