Metadata-Version: 2.1
Name: dekdjselfmigration
Version: 0.1.12
Author-Email: sanzenwin <sanzenwin@gmail.com>
License: MIT
Requires-Python: >=3.10
Requires-Dist: dekdjtools<1.0.0
